{
  "posts": [
    {
      "id": "d9aa9cb7-1112-4eea-8d51-946d9887b0c7",
      "slug": "birthday",
      "title": "Next.js 13 App Router A New Era of React Applications",
      "description": "A comprehensive guide to Next.js 13's App Router and how it reshapes routing in React apps.",
      "tags": [
        "tech"
      ],
      "publishDate": "2024-09-18T00:00:00.000Z",
      "readingTime": "4 min read",
      "uploaded": "2024-09-18T00:00:00.000Z",
      "tag": "tech",
      "heroImage": "https://res.cloudinary.com/dbbi1d6wo/image/upload/v1729817350/post2_vpelv3.jpg"
    },
    {
      "id": "724eb3d7-2b90-4620-a73e-37431ea7617e",
      "slug": "hello",
      "title": "React Hooks Deep Dive Transforming Functional Components",
      "description": "Explore how React hooks have transformed the way we write functional components in modern React applications.",
      "tags": [
        "tech"
      ],
      "publishDate": "2024-09-18T00:00:00.000Z",
      "readingTime": "4 min read",
      "uploaded": "2024-09-18T00:00:00.000Z",
      "tag": "tech",
      "heroImage": "https://res.cloudinary.com/dbbi1d6wo/image/upload/v1729817347/post3_ctmv8j.jpg"
    },
    {
      "id": "8759b76e-767e-49ee-a912-f7a797be1c61",
      "slug": "ai",
      "title": "TypeScript Best Practices Writing Cleaner, Safer Code",
      "description": "Learn key best practices for writing clean and type-safe TypeScript code.",
      "tags": [
        "web-development"
      ],
      "publishDate": "2024-11-20T00:00:00.000Z",
      "readingTime": "6 min read",
      "uploaded": "2024-11-20T00:00:00.000Z",
      "tag": "web-development",
      "heroImage": "https://res.cloudinary.com/dbbi1d6wo/image/upload/v1729817345/post1_k3q3d8.jpg"
    },
    {
      "id": "e911ff4c-e9c0-4c83-81d4-717bc2695352",
      "slug": "small",
      "title": "what then?",
      "description": "Is this thing working?",
      "tags": [
        "abstract"
      ],
      "publishDate": "1970-01-01T00:00:00.000Z",
      "readingTime": "1 min read",
      "uploaded": "1970-01-01T00:00:00.000Z",
      "tag": "abstract",
      "heroImage": "https://res.cloudinary.com/dbbi1d6wo/image/upload/v1729817346/post4_yp8isz.jpg"
    }
  ],
  "tags": {
    "popular": [
      "small",
      "hello",
      "birthday",
      "ai"
    ],
    "latest": [
      "ai",
      "birthday",
      "hello",
      "small"
    ],
    "top": [
      "birthday",
      "hello",
      "ai"
    ],
    "web-development": [
      "ai"
    ],
    "tech": [
      "birthday",
      "hello"
    ],
    "abstract": [
      "small"
    ]
  }
}